krishpy/__init__.py
krishpy/example.py
krishpy-0.1.0.dist-info/WHEEL
krishpy-0.1.0.dist-info/METADATA
krishpy-0.1.0.dist-info/RECORD
