Metadata-Version: 2.1
Name: krishpy
Version: 0.1.0
Summary: new project
Author-email: Krish <krishpy3@gmail.com>
Requires-Python: >=3.10
Requires-Dist: requests>=2.31.0
Requires-Dist: boto3>=1.29.1
Requires-Dist: pydantic>=2.5.1
